Metadata-Version: 1.0
Name: djando
Version: 0.1
Summary: Using Docker with Django made easy
Home-page: http://github.com/rayronvictor/djando
Author: Rayron Victor
Author-email: rayronvictor@gmail.com
License: MIT
Platform: UNKNOWN
